openmodes/__init__.py
openmodes/array.py
openmodes/basis.py
openmodes/constants.py
openmodes/core.cp37-win_amd64.pyd
openmodes/dunavant.cp37-win_amd64.pyd
openmodes/eig.py
openmodes/helpers.py
openmodes/impedance.py
openmodes/integration.py
openmodes/ipython.py
openmodes/libifcoremd.dll
openmodes/libiomp5md.dll
openmodes/libmmd.dll
openmodes/material.py
openmodes/model.py
openmodes/modes.py
openmodes/multipole.py
openmodes/parts.py
openmodes/simulation.py
openmodes/sources.py
openmodes/svml_dispmd.dll
openmodes/version.py
openmodes/visualise.py
openmodes/external/__init__.py
openmodes/external/ordered_set.py
openmodes/external/point_in_polygon.py
openmodes/external/three.js/CanvasRenderer.js
openmodes/external/three.js/Detector.js
openmodes/external/three.js/LICENSE
openmodes/external/three.js/Lut.js
openmodes/external/three.js/OrbitControls.js
openmodes/external/three.js/Projector.js
openmodes/external/three.js/README.md
openmodes/external/three.js/three.min.js
openmodes/geometry/SRR.geo
openmodes/geometry/asymmetric_ring.geo
openmodes/geometry/box.geo
openmodes/geometry/canonical_spiral.geo
openmodes/geometry/circle.geo
openmodes/geometry/circled_cross.geo
openmodes/geometry/closed_ring.geo
openmodes/geometry/cross.geo
openmodes/geometry/cylinder_hole.geo
openmodes/geometry/cylinder_hollow.geo
openmodes/geometry/cylinder_rounded.geo
openmodes/geometry/ellipsoid.geo
openmodes/geometry/elliptical_cylinder.geo
openmodes/geometry/horseshoe_rect.geo
openmodes/geometry/isosceles.geo
openmodes/geometry/rectangle.geo
openmodes/geometry/single-bent.geo
openmodes/geometry/single.geo
openmodes/geometry/solid_L.geo
openmodes/geometry/sphere.geo
openmodes/geometry/torus.geo
openmodes/geometry/v_antenna.geo
openmodes/mesh/__init__.py
openmodes/mesh/freecad.py
openmodes/mesh/gmsh.py
openmodes/mesh/mesh.py
openmodes/operator/__init__.py
openmodes/operator/operator.py
openmodes/operator/pec.py
openmodes/operator/penetrable.py
openmodes/operator/rwg.py
OpenModes-1.3.2.dist-info/LICENSE.txt
OpenModes-1.3.2.dist-info/METADATA
OpenModes-1.3.2.dist-info/WHEEL
OpenModes-1.3.2.dist-info/top_level.txt
OpenModes-1.3.2.dist-info/RECORD
