Metadata-Version: 2.1
Name: OpenModes
Version: 1.3.2
Summary: An eigenmode solver for open electromagnetic resonantors
Home-page: http://davidpowell.github.io/OpenModes
Author: David Powell
Author-email: DavidAnthonyPowell@gmail.com
License: GPLv3+
Platform: Windows
Platform: Linux
Classifier: Development Status :: 4 - Beta
Classifier: Environment :: Console
Classifier: Environment :: Web Environment
Classifier: Intended Audience :: Science/Research
Classifier: Intended Audience :: Developers
Classifier: License :: OSI Approved :: GNU General Public License v3 or later (GPLv3+)
Classifier: Operating System :: Microsoft :: Windows
Classifier: Operating System :: POSIX
Classifier: Programming Language :: Python :: 3.3
Classifier: Programming Language :: Python :: 3.4
Classifier: Programming Language :: Python :: 3.5
Classifier: Programming Language :: Python :: 3.6
Classifier: Programming Language :: Python :: 3.7
Classifier: Programming Language :: Fortran
Classifier: Topic :: Scientific/Engineering
Requires-Dist: numpy (>=1.10.0)
Requires-Dist: scipy (>=0.18.0)
Requires-Dist: matplotlib
Requires-Dist: jinja2
Requires-Dist: six
Requires-Dist: ipywidgets
Requires-Dist: meshio
Requires-Dist: dill
